netbox_validity-3.4.0.dist-info/licenses/LICENSE
validity/__init__.py
validity/admin.py
validity/choices.py
validity/custom_validators.py
validity/data_backends.py
validity/dependencies.py
validity/filtersets.py
validity/j2_env.py
validity/managers.py
validity/model_validators.py
validity/navigation.py
validity/search.py
validity/settings.py
validity/signals.py
validity/subforms.py
validity/tables.py
validity/template_content.py
validity/urls.py
validity/api/__init__.py
validity/api/helpers.py
validity/api/serializers.py
validity/api/urls.py
validity/api/views.py
validity/compliance/dynamic_pairs.py
validity/compliance/exceptions.py
validity/compliance/state.py
validity/compliance/eval/__init__.py
validity/compliance/eval/default_nameset.py
validity/compliance/eval/eval.py
validity/compliance/eval/eval_defaults.py
validity/compliance/serialization/__init__.py
validity/compliance/serialization/backend.py
validity/compliance/serialization/common.py
validity/compliance/serialization/routeros.py
validity/compliance/serialization/serializable.py
validity/compliance/serialization/textfsm.py
validity/compliance/serialization/ttp.py
validity/compliance/serialization/xml.py
validity/compliance/serialization/yaml.py
validity/data_backup/__init__.py
validity/data_backup/backend.py
validity/data_backup/backupers.py
validity/data_backup/entities.py
validity/data_backup/parameters.py
validity/fields/__init__.py
validity/fields/encrypted.py
validity/forms/__init__.py
validity/forms/bulk_import.py
validity/forms/fields.py
validity/forms/filterset.py
validity/forms/general.py
validity/forms/mixins.py
validity/forms/widgets.py
validity/graphql/__init__.py
validity/graphql/filters.py
validity/graphql/schema.py
validity/graphql/types.py
validity/integrations/data_models.py
validity/integrations/errors.py
validity/integrations/git.py
validity/integrations/s3.py
validity/migrations/0010_squashed_initial.py
validity/migrations/0011_delete_scripts.py
validity/migrations/0012_backuppoint_devicerole.py
netbox_validity-3.4.0.dist-info/METADATA
netbox_validity-3.4.0.dist-info/WHEEL
netbox_validity-3.4.0.dist-info/top_level.txt
netbox_validity-3.4.0.dist-info/RECORD
