Metadata-Version: 2.4
Name: netbox-validity
Version: 3.4.0
Summary: NetBox plugin for network devices validation
Author-email: Anton Miasnikov <anton2008m@gmail.com>
License: MIT License
Classifier: Development Status :: 5 - Production/Stable
Classifier: Programming Language :: Python
Classifier: Programming Language :: Python :: Implementation :: CPython
Classifier: Programming Language :: Python :: 3
Classifier: Programming Language :: Python :: 3 :: Only
Classifier: Intended Audience :: System Administrators
Classifier: Intended Audience :: Telecommunications Industry
Classifier: License :: OSI Approved :: MIT License
Classifier: Operating System :: Unix
Classifier: Operating System :: POSIX :: Linux
Classifier: Framework :: Django
Classifier: Topic :: System :: Networking
Classifier: Topic :: Internet
Requires-Python: >=3.10
License-File: LICENSE
Requires-Dist: boto3<2
Requires-Dist: deepdiff<9,>=8.6.1
Requires-Dist: dimi<2,>=1.5.0
Requires-Dist: django-bootstrap5<25,>=24.2
Requires-Dist: dulwich
Requires-Dist: jq<2,>=1.4.0
Requires-Dist: netmiko<5,>=4.0.0
Requires-Dist: pydantic<3,>=2.0.0
Requires-Dist: scrapli_netconf==2026.1.12
Requires-Dist: simpleeval==1.0.3
Requires-Dist: textfsm<2,>=1.1.3
Requires-Dist: ttp<1
Requires-Dist: xmltodict<1
Provides-Extra: dev
Requires-Dist: debugpy==1.8.19; extra == "dev"
Requires-Dist: factory_boy==3.3.3; extra == "dev"
Requires-Dist: ipython; extra == "dev"
Requires-Dist: pre-commit==4.5.1; extra == "dev"
Requires-Dist: pytest==9.0.2; extra == "dev"
Requires-Dist: pytest-cov==7.0.0; extra == "dev"
Requires-Dist: pytest-django==4.11.1; extra == "dev"
Requires-Dist: pytest-subtests==0.15.0; extra == "dev"
Requires-Dist: ruff==0.14.11; extra == "dev"
Requires-Dist: tomli==2.4.0; extra == "dev"
Provides-Extra: docs
Requires-Dist: mkdocs==1.6.1; extra == "docs"
Requires-Dist: mkdocs-include-markdown-plugin==7.1.8; extra == "docs"
Requires-Dist: mkdocs-material==9.5.34; extra == "docs"
Dynamic: license-file
